Metadata-Version: 2.1
Name: qiskit-quaintier
Version: 0.3.0
Summary: A quantum provider for Qiskit
Classifier: Programming Language :: Python :: 3
Classifier: License :: OSI Approved :: MIT License
Classifier: Operating System :: OS Independent
Requires-Python: >=3.6
